kozmoserver/__init__.py
kozmoserver/batch_processing.py
kozmoserver/batching/__init__.py
kozmoserver/batching/adaptive.py
kozmoserver/batching/hooks.py
kozmoserver/batching/requests.py
kozmoserver/batching/shape.py
kozmoserver/cache/__init__.py
kozmoserver/cache/cache.py
kozmoserver/cache/local/__init__.py
kozmoserver/cache/local/local.py
kozmoserver/cli/__init__.py
kozmoserver/cli/build.py
kozmoserver/cli/constants.py
kozmoserver/cli/init_project.py
kozmoserver/cli/main.py
kozmoserver/cli/serve.py
kozmoserver/cloudevents.py
kozmoserver/codecs/__init__.py
kozmoserver/codecs/base.py
kozmoserver/codecs/base64.py
kozmoserver/codecs/datetime.py
kozmoserver/codecs/decorator.py
kozmoserver/codecs/errors.py
kozmoserver/codecs/lists.py
kozmoserver/codecs/numpy.py
kozmoserver/codecs/pandas.py
kozmoserver/codecs/string.py
kozmoserver/codecs/utils.py
kozmoserver/context.py
kozmoserver/env.py
kozmoserver/errors.py
kozmoserver/grpc/__init__.py
kozmoserver/grpc/converters.py
kozmoserver/grpc/dataplane_pb2.py
kozmoserver/grpc/dataplane_pb2.pyi
kozmoserver/grpc/dataplane_pb2_grpc.py
kozmoserver/grpc/interceptors.py
kozmoserver/grpc/logging.py
kozmoserver/grpc/model_repository.py
kozmoserver/grpc/model_repository_pb2.py
kozmoserver/grpc/model_repository_pb2.pyi
kozmoserver/grpc/model_repository_pb2_grpc.py
kozmoserver/grpc/server.py
kozmoserver/grpc/servicers.py
kozmoserver/grpc/utils.py
kozmoserver/handlers/__init__.py
kozmoserver/handlers/custom.py
kozmoserver/handlers/dataplane.py
kozmoserver/handlers/model_repository.py
kozmoserver/kafka/__init__.py
kozmoserver/kafka/errors.py
kozmoserver/kafka/handlers.py
kozmoserver/kafka/logging.py
kozmoserver/kafka/message.py
kozmoserver/kafka/server.py
kozmoserver/logging.py
kozmoserver/metrics/__init__.py
kozmoserver/metrics/context.py
kozmoserver/metrics/errors.py
kozmoserver/metrics/logging.py
kozmoserver/metrics/prometheus.py
kozmoserver/metrics/registry.py
kozmoserver/metrics/server.py
kozmoserver/middleware.py
kozmoserver/model.py
kozmoserver-0.1.0.dist-info/LICENSE
kozmoserver-0.1.0.dist-info/LICENSES/license.txt
kozmoserver-0.1.0.dist-info/LICENSES/license_info.csv
kozmoserver-0.1.0.dist-info/LICENSES/license_info.no_versions.csv
kozmoserver-0.1.0.dist-info/METADATA
kozmoserver-0.1.0.dist-info/WHEEL
kozmoserver-0.1.0.dist-info/entry_points.txt
kozmoserver-0.1.0.dist-info/RECORD
